jupyterlab_dagitty/__init__.py
jupyterlab_dagitty/_version.py
jupyterlab_dagitty/dag.py
jupyterlab_dagitty/py.typed
jupyterlab_dagitty/labextension/package.json
jupyterlab_dagitty/labextension/static/549.bd38247095d457759067.js
jupyterlab_dagitty/labextension/static/794.3d9dfba1e78b8c80bec8.js
jupyterlab_dagitty/labextension/static/868.0eeb4a6e7d9667f6e1b5.js
jupyterlab_dagitty/labextension/static/remoteEntry.08ba860ce2279ff6767f.js
jupyterlab_dagitty/labextension/static/style.js
jupyterlab_dagitty/labextension/static/third-party-licenses.json
jupyterlab_dagitty-0.3.5.data/data/share/jupyter/labextensions/jupyterlab-dagitty/install.json
jupyterlab_dagitty-0.3.5.data/data/share/jupyter/labextensions/jupyterlab-dagitty/package.json
jupyterlab_dagitty-0.3.5.data/data/share/jupyter/labextensions/jupyterlab-dagitty/static/549.bd38247095d457759067.js
jupyterlab_dagitty-0.3.5.data/data/share/jupyter/labextensions/jupyterlab-dagitty/static/794.3d9dfba1e78b8c80bec8.js
jupyterlab_dagitty-0.3.5.data/data/share/jupyter/labextensions/jupyterlab-dagitty/static/868.0eeb4a6e7d9667f6e1b5.js
jupyterlab_dagitty-0.3.5.data/data/share/jupyter/labextensions/jupyterlab-dagitty/static/remoteEntry.08ba860ce2279ff6767f.js
jupyterlab_dagitty-0.3.5.data/data/share/jupyter/labextensions/jupyterlab-dagitty/static/style.js
jupyterlab_dagitty-0.3.5.data/data/share/jupyter/labextensions/jupyterlab-dagitty/static/third-party-licenses.json
jupyterlab_dagitty-0.3.5.dist-info/LICENSE
jupyterlab_dagitty-0.3.5.dist-info/METADATA
jupyterlab_dagitty-0.3.5.dist-info/WHEEL
jupyterlab_dagitty-0.3.5.dist-info/top_level.txt
jupyterlab_dagitty-0.3.5.dist-info/RECORD
